README.rst
setup.cfg
setup.py
Flask_Gulp.egg-info/PKG-INFO
Flask_Gulp.egg-info/SOURCES.txt
Flask_Gulp.egg-info/dependency_links.txt
Flask_Gulp.egg-info/requires.txt
Flask_Gulp.egg-info/top_level.txt
flask_gulp/__init__.py
flask_gulp/extensions.py
flask_gulp/static.py
flask_gulp/watcher.py
flask_gulp/wildcard.py