Metadata-Version: 1.1
Name: Flask-Gulp
Version: 0.3.0
Summary: Task executioner similar to gulp for Python
Home-page: https://github.com/rolurq/flask-gulp
Author: Rolando Urquiza
Author-email: rolurquiza@gmail.com
License: MIT License
Keywords: flask gulp task watcher
Platform: any
Classifier: Environment :: Web Environment
Classifier: Intended Audience :: Developers
Classifier: Operating System :: OS Independent
Classifier: Programming Language :: Python
Classifier: Topic :: Software Development :: Libraries
Classifier: Topic :: Utilities
